<?xml version="1.0" encoding="windows-1252"?>
<!--CymdistXML file generated by Cymdist 5.02 07-->
<!--Copyright (c) 2009 CYME International inc. (www.cyme.com)-->
<Cyme>
<Cymdist>
<SchemaVersion>1</SchemaVersion>
<CymdistProperties>
<Version>5.02</Version>
<Revision>07</Revision>
</CymdistProperties>
<DatabaseConnections>
<DatabaseConnection>
<Name>Eastern502</Name>
<EquipmentType>Access</EquipmentType>
<EquipmentDataSource>
<MDBDataSource>
<FileName>C:\CorpApps\CYME Models\Eastern502.mdb</FileName>
</MDBDataSource>
</EquipmentDataSource>
<NetworkType>Access</NetworkType>
<NetworkDataSource>
<MDBDataSource>
<FileName>C:\CorpApps\CYME Models\Eastern502.mdb</FileName>
</MDBDataSource>
</NetworkDataSource>
<StudyDirectory/>
<DefaultLoadModel/>
</DatabaseConnection>
<DatabaseConnection>
<Name>North-HENZB502</Name>
<EquipmentType>Access</EquipmentType>
<EquipmentDataSource>
<MDBDataSource>
<FileName>C:\CorpApps\CYME Models\North-HENZB502.mdb</FileName>
</MDBDataSource>
</EquipmentDataSource>
<NetworkType>Access</NetworkType>
<NetworkDataSource>
<MDBDataSource>
<FileName>C:\CorpApps\CYME Models\North-HENZB502.mdb</FileName>
</MDBDataSource>
</NetworkDataSource>
<StudyDirectory/>
<DefaultLoadModel/>
</DatabaseConnection>
<DatabaseConnection>
<Name>North-Metro502</Name>
<EquipmentType>Access</EquipmentType>
<EquipmentDataSource>
<MDBDataSource>
<FileName>C:\CorpApps\CYME Models\North-Metro502.mdb</FileName>
</MDBDataSource>
</EquipmentDataSource>
<NetworkType>Access</NetworkType>
<NetworkDataSource>
<MDBDataSource>
<FileName>C:\CorpApps\CYME Models\North-Metro502.mdb</FileName>
</MDBDataSource>
</NetworkDataSource>
<StudyDirectory/>
<DefaultLoadModel/>
</DatabaseConnection>
<DatabaseConnection>
<Name>Southern502</Name>
<EquipmentType>Access</EquipmentType>
<EquipmentDataSource>
<MDBDataSource>
<FileName>C:\CorpApps\CYME Models\Southern502.mdb</FileName>
</MDBDataSource>
</EquipmentDataSource>
<NetworkType>Access</NetworkType>
<NetworkDataSource>
<MDBDataSource>
<FileName>C:\CorpApps\CYME Models\Southern502.mdb</FileName>
</MDBDataSource>
</NetworkDataSource>
<StudyDirectory/>
<DefaultLoadModel/>
</DatabaseConnection>
<DatabaseConnection>
<Name>Western502</Name>
<EquipmentType>Access</EquipmentType>
<EquipmentDataSource>
<MDBDataSource>
<FileName>C:\CorpApps\CYME Models\Western502.mdb</FileName>
</MDBDataSource>
</EquipmentDataSource>
<NetworkType>Access</NetworkType>
<NetworkDataSource>
<MDBDataSource>
<FileName>C:\CorpApps\CYME Models\Western502.mdb</FileName>
</MDBDataSource>
</NetworkDataSource>
<StudyDirectory/>
<DefaultLoadModel/>
</DatabaseConnection>
</DatabaseConnections>
</Cymdist>
</Cyme>
